pyggyback/SocketServer.py
pyggyback/__init__.py
pyggyback/deamon_marechal.py
pyggyback/lru_cache.py
pyggyback/manifold_learning_on_digits.py
pyggyback/mkcodes.py
pyggyback/module_dependencies.py
pyggyback/plot.py
pyggyback/pype.py
pyggyback/pytrends.py
pyggyback/smote.py
pyggyback/triangle.py
pyggyback/zipmod.py
pyggyback/mo2s3/__init__.py
pyggyback/mo2s3/core.py
pyggyback-0.0.3.dist-info/LICENSE
pyggyback-0.0.3.dist-info/METADATA
pyggyback-0.0.3.dist-info/WHEEL
pyggyback-0.0.3.dist-info/top_level.txt
pyggyback-0.0.3.dist-info/RECORD
